LibSerial20
