Metadata-Version: 1.1
Name: LibSerial20
Version: 0.4
Summary: Biblioteca LibSerial20 
Home-page: https://github.com/DiviKnight/LibSerial20
Author: Wesley
Author-email: diviwfel@gmail.com
License: MIT
Download-URL: https://github.com/DiviKnight/LibSerial20/archive/0.4.tar.gz
Keywords: Serial,Senai,ComPort
Platform: UNKNOWN
Classifier: Development Status :: 5 - Production/Stable
Classifier: Intended Audience :: Developers
Classifier: Topic :: Software Development :: Build Tools
Classifier: License :: OSI Approved :: MIT License
Classifier: Programming Language :: Python :: 3
Classifier: Programming Language :: Python :: 3.7
